{
	"1": {
		"order": {
			"clientId": "2",
			"dateCreated": "2018-09-02 15:35:15",
			"dateUpdated": "2018-09-03 4:07:00",
			"complete": "false",
			"comlete": true
		},
		"products": [
			{
				"5": {
					"title": "1TB Playstation 4 Console (Black) + God Of War Game Bundle (PS4)",
					"description": "Journey to the wilds of Midgard in stunning HDR and do battle with ferocious creatures from Norse mythology with the God of War 1TB PS4 bundle.",
					"price": "5999",
					"image": "https://media.takealot.com/covers_tsins/52348455/711719384977-1-xlpreview.jpg?1520499970",
					"quantity": "1"
				},
				"8": {
					"title": "Playstation 4 1TB Console + Marvels Spider-man Game (PS4)",
					"description": "Be greater and explore a new chapter in Marvel’s Spider-Man universe in HDR quality graphics with the Marvel’s Spider-Man bundle on PlayStation 4. Starring one of the world’s most iconic Super Heroes, Marvels Spider-Man.",
					"price": "5999",
					"image": "https://media.takealot.com/covers_tsins/55225566/711719741213-1-xlpreview.jpg?1532943725",
					"quantity": "2"
				}
			}
		]
	}
}